[
  {
    "question": "مبسوطه يحبيبتي؟",
    "answer": "لا مش مبسوطه ",
    "date": "2025-01-25T19:08:44.686Z"
  },
  {
    "question": "متضايقة من حاجة؟",
    "answer": "لأ، الحمد لله",
    "date": "2025-01-25T19:08:46.147Z"
  },
  {
    "question": "عاوزة تقوليلي حاجة؟",
    "answer": "لأ مش عاوزة",
    "date": "2025-01-25T19:08:46.918Z"
  },
  {
    "question": "مبسوطه يحبيبتي؟",
    "answer": "لا مش مبسوطه ",
    "date": "2025-01-25T19:13:39.564Z"
  },
  {
    "question": "متضايقة من حاجة؟",
    "answer": "لأ، الحمد لله",
    "date": "2025-01-25T19:13:41.960Z"
  },
  {
    "question": "عاوزة تقوليلي حاجة؟",
    "answer": "لأ مش عاوزة",
    "date": "2025-01-25T19:13:42.578Z"
  },
  {
    "question": "مبسوطه يحبيبتي؟",
    "answer": " مبسوطه يحبيبي",
    "date": "2025-01-25T19:14:20.634Z"
  },
  {
    "question": "متضايقة من حاجة؟",
    "answer": "لأ، الحمد لله",
    "date": "2025-01-25T19:14:20.938Z"
  },
  {
    "question": "عاوزة تقوليلي حاجة؟",
    "answer": "لأ مش عاوزة",
    "date": "2025-01-25T19:14:21.835Z"
  },
  {
    "question": "مبسوطه يحبيبتي؟",
    "answer": " مبسوطه يحبيبي",
    "date": "2025-01-25T19:15:35.854Z"
  },
  {
    "question": "متضايقة من حاجة؟",
    "answer": "لأ، الحمد لله",
    "date": "2025-01-25T19:15:36.137Z"
  },
  {
    "question": "عاوزة تقوليلي حاجة؟",
    "answer": "لأ مش عاوزة",
    "date": "2025-01-25T19:15:36.650Z"
  },
  {
    "question": "مبسوطه يحبيبتي؟",
    "answer": " مبسوطه يحبيبي",
    "date": "2025-01-25T19:15:49.429Z"
  },
  {
    "question": "متضايقة من حاجة؟",
    "answer": "لأ، الحمد لله",
    "date": "2025-01-25T19:15:49.662Z"
  },
  {
    "question": "عاوزة تقوليلي حاجة؟",
    "answer": "لأ مش عاوزة",
    "date": "2025-01-25T19:15:49.909Z"
  },
  {
    "question": "مبسوطه يحبيبتي؟",
    "answer": " مبسوطه يحبيبي",
    "date": "2025-01-25T19:35:16.156Z"
  },
  {
    "question": "متضايقة من حاجة؟",
    "answer": "لأ، الحمد لله",
    "date": "2025-01-25T19:35:16.608Z"
  },
  {
    "question": "عاوزة تقوليلي حاجة؟",
    "answer": "لأ مش عاوزة",
    "date": "2025-01-25T19:35:17.336Z"
  },
  {
    "question": "مبسوطه يحبيبتي؟",
    "answer": " مبسوطه يحبيبي",
    "date": "2025-01-25T19:37:48.708Z"
  },
  {
    "question": "متضايقة من حاجة؟",
    "answer": "لأ، الحمد لله",
    "date": "2025-01-25T19:37:49.384Z"
  },
  {
    "question": "عاوزة تقوليلي حاجة؟",
    "answer": "لأ مش عاوزة",
    "date": "2025-01-25T19:37:49.933Z"
  },
  {
    "question": "مبسوطه يحبيبتي؟",
    "answer": " مبسوطه يحبيبي",
    "date": "2025-01-25T19:39:28.752Z"
  },
  {
    "question": "متضايقة من حاجة؟",
    "answer": "لأ، الحمد لله",
    "date": "2025-01-25T19:39:29.368Z"
  },
  {
    "question": "عاوزة تقوليلي حاجة؟",
    "answer": "لأ مش عاوزة",
    "date": "2025-01-25T19:39:29.895Z"
  },
  {
    "question": "مبسوطه يحبيبتي؟",
    "answer": "لا مش مبسوطه ",
    "date": "2025-01-25T19:41:38.435Z"
  },
  {
    "question": "متضايقة من حاجة؟",
    "answer": "لأ، الحمد لله",
    "date": "2025-01-25T19:41:41.793Z"
  },
  {
    "question": "عاوزة تقوليلي حاجة؟",
    "answer": "لأ مش عاوزة",
    "date": "2025-01-25T19:41:43.243Z"
  },
  {
    "question": "مبسوطه يحبيبتي؟",
    "answer": "لا مش مبسوطه ",
    "date": "2025-01-25T19:42:43.393Z"
  },
  {
    "question": "متضايقة من حاجة؟",
    "answer": "لأ، الحمد لله",
    "date": "2025-01-25T19:42:44.689Z"
  },
  {
    "question": "عاوزة تقوليلي حاجة؟",
    "answer": "لأ مش عاوزة",
    "date": "2025-01-25T19:42:45.196Z"
  },
  {
    "question": "مبسوطه يحبيبتي؟",
    "answer": " مبسوطه يحبيبي",
    "date": "2025-01-25T19:44:12.977Z"
  },
  {
    "question": "متضايقة من حاجة؟",
    "answer": "لأ، الحمد لله",
    "date": "2025-01-25T19:44:13.656Z"
  },
  {
    "question": "عاوزة تقوليلي حاجة؟",
    "answer": "لأ مش عاوزة",
    "date": "2025-01-25T19:44:14.193Z"
  }
]